super_sparql/__init__.py
super_sparql/main.py
super_sparql-0.1.0.dist-info/LICENSE
super_sparql-0.1.0.dist-info/METADATA
super_sparql-0.1.0.dist-info/WHEEL
super_sparql-0.1.0.dist-info/top_level.txt
super_sparql-0.1.0.dist-info/RECORD
