Metadata-Version: 2.2
Name: super_sparql
Version: 0.1.0
Summary: This package is for parsing the SPARQL Queries in order to save the world
Author: Vicky Vicky
License: MIT
Classifier: Programming Language :: Python :: 3
Classifier: License :: OSI Approved :: MIT License
Classifier: Operating System :: OS Independent
Requires-Python: >=3.7
License-File: LICENSE
Dynamic: author
Dynamic: classifier
Dynamic: description
Dynamic: description-content-type
Dynamic: license
Dynamic: requires-python
Dynamic: summary
